mafese/__init__.py
mafese/filter.py
mafese/selector.py
mafese/unsupervised.py
mafese/data/cls/Arrhythmia.csv
mafese/data/cls/Blood.csv
mafese/data/cls/BreastCancer.csv
mafese/data/cls/BreastEW.csv
mafese/data/cls/CongressEW.csv
mafese/data/cls/Digits.csv
mafese/data/cls/Glass.csv
mafese/data/cls/HeartEW.csv
mafese/data/cls/Hill-valley.csv
mafese/data/cls/Horse.csv
mafese/data/cls/Ionosphere.csv
mafese/data/cls/Iris.csv
mafese/data/cls/Lymphography.csv
mafese/data/cls/Madelon.csv
mafese/data/cls/Monk1.csv
mafese/data/cls/Monk2.csv
mafese/data/cls/Monk3.csv
mafese/data/cls/Sonar.csv
mafese/data/cls/Soybean-small.csv
mafese/data/cls/SpectEW.csv
mafese/data/cls/Tic-tac-toe.csv
mafese/data/cls/Vowel.csv
mafese/data/cls/WaveformEW.csv
mafese/data/cls/Wine.csv
mafese/data/cls/Zoo.csv
mafese/data/cls/aggregation.csv
mafese/data/cls/aniso.csv
mafese/data/cls/appendicitis.csv
mafese/data/cls/balance.csv
mafese/data/cls/banknote.csv
mafese/data/cls/blobs.csv
mafese/data/cls/circles.csv
mafese/data/cls/diagnosis_II.csv
mafese/data/cls/ecoli.csv
mafese/data/cls/flame.csv
mafese/data/cls/heart.csv
mafese/data/cls/jain.csv
mafese/data/cls/liver.csv
mafese/data/cls/moons.csv
mafese/data/cls/mouse.csv
mafese/data/cls/pathbased.csv
mafese/data/cls/seeds.csv
mafese/data/cls/smiley.csv
mafese/data/cls/varied.csv
mafese/data/cls/vary-density.csv
mafese/data/cls/vertebral2.csv
mafese/data/cls/wdbc.csv
mafese/data/reg/boston-housing.csv
mafese/data/reg/computer-hardware.csv
mafese/data/reg/diabetes.csv
mafese/data/reg/gauss-100-20.csv
mafese/data/reg/gauss-50-12.csv
mafese/data/reg/gauss-75-17.csv
mafese/data/reg/linnerud.csv
mafese/embedded/__init__.py
mafese/embedded/lasso.py
mafese/embedded/tree.py
mafese/utils/__init__.py
mafese/utils/correlation.py
mafese/utils/data_loader.py
mafese/utils/encoder.py
mafese/utils/estimator.py
mafese/utils/evaluator.py
mafese/utils/mealpy_util.py
mafese/utils/scaler.py
mafese/utils/transfer.py
mafese/utils/validator.py
mafese/wrapper/__init__.py
mafese-1.0.0.dist-info/licenses/LICENSE
mafese-1.0.0.dist-info/METADATA
mafese-1.0.0.dist-info/WHEEL
mafese-1.0.0.dist-info/top_level.txt
mafese-1.0.0.dist-info/RECORD
